blackt/__init__.py
blackt/__main__.py
blackt-2024.0.2.dist-info/entry_points.txt
blackt-2024.0.2.dist-info/LICENSE.md
blackt-2024.0.2.dist-info/METADATA
blackt-2024.0.2.dist-info/WHEEL
blackt-2024.0.2.dist-info/RECORD
