Metadata-Version: 2.1
Name: blackt
Version: 2024.0.2
Summary: Black but with tabs
Home-page: https://github.com/FHPythonUtils/blackt
License: MIT
Author: FredHappyface
Requires-Python: >=3.10,<4.0
Classifier: Development Status :: 5 - Production/Stable
Classifier: Intended Audience :: Developers
Classifier: Intended Audience :: Education
Classifier: License :: OSI Approved :: MIT License
Classifier: Natural Language :: English
Classifier: Operating System :: OS Independent
Classifier: Programming Language :: Python :: 3
Classifier: Programming Language :: Python :: 3.10
Classifier: Programming Language :: Python :: 3.11
Classifier: Programming Language :: Python :: 3.12
Classifier: Programming Language :: Python :: Implementation :: CPython
Classifier: Topic :: Software Development :: Libraries :: Python Modules
Classifier: Topic :: Utilities
Requires-Dist: black (>=24.3.0,<25)
Project-URL: Documentation, https://github.com/FHPythonUtils/blackt/blob/master/README.md
Project-URL: Repository, https://github.com/FHPythonUtils/blackt
